easy_money/__init__.py
candid_cash-23.10.0b4.dist-info/LICENSE
candid_cash-23.10.0b4.dist-info/METADATA
candid_cash-23.10.0b4.dist-info/WHEEL
candid_cash-23.10.0b4.dist-info/entry_points.txt
candid_cash-23.10.0b4.dist-info/top_level.txt
candid_cash-23.10.0b4.dist-info/RECORD
