Metadata-Version: 2.1
Name: candid-cash
Version: 23.10.0b4
Summary: Tool for budgeting/tracking finances.
Author-email: Wayne Werner <wayne@waynewerner.com>
Keywords: money,finance,budget,productivity
Classifier: Development Status :: 3 - Alpha
Classifier: Environment :: Console
Classifier: Environment :: Web Environment
Classifier: License :: OSI Approved :: GNU Affero General Public License v3 or later (AGPLv3+)
Classifier: Programming Language :: Python :: 3.8
Classifier: Programming Language :: Python :: 3.9
Classifier: Programming Language :: Python :: 3.10
Classifier: Programming Language :: Python :: 3.11
Classifier: Programming Language :: Python :: 3.12
Classifier: Topic :: Office/Business
Classifier: Topic :: Utilities
Classifier: Topic :: Office/Business :: Financial :: Accounting
Classifier: Intended Audience :: End Users/Desktop
License-File: LICENSE
